nth/__init__.py
nth/__main__.py
nth/_utils.py
nth/lookup.py
nth/nthalize.py
nth/number.py
nth/py.typed
nth-0.1.8.dist-info/entry_points.txt
nth-0.1.8.dist-info/WHEEL
nth-0.1.8.dist-info/METADATA
nth-0.1.8.dist-info/RECORD
